{
  "configs": [
    {
      "id": 1,
      "title": "Telemed",
      "system": "IOS Push"
    },
    {
      "id": 2,
      "title": "Telemed",
      "system": "IOS Push"
    },
    {
      "id": 3,
      "title": "Telemed",
      "system": "IOS Push"
    }
  ],
  "users": [
    {
      "firstName": "typi",
      "lastName": "code",
      "mail": "typicode@mail.com",
      "password": "123123"
    },
    {
      "firstName": "code",
      "lastName": "typi",
      "mail": "codetypi@mail.com",
      "password": "321321"
    },
    {
      "firstName": "Илья",
      "lastName": "Андреевич",
      "email": "ilya-andreevi4@mail.ru",
      "password": "123123"
    }
  ]
}